README.md
setup.py
gaia_utils/__init__.py
gaia_utils/auth.py
gaia_utils/bigquery_utils.py
gaia_utils/common.py
gaia_utils/contants.py
gaia_utils/env.py
gaia_utils/user_table.py
gaia_utils/utils.py
gaia_utils.egg-info/PKG-INFO
gaia_utils.egg-info/SOURCES.txt
gaia_utils.egg-info/dependency_links.txt
gaia_utils.egg-info/requires.txt
gaia_utils.egg-info/top_level.txt
gaia_utils/enumlib/__init__.py
gaia_utils/enumlib/bigquery_schema_type_enum.py
gaia_utils/enumlib/load_data_frame_type_enum.py